{
  "legislative_session": "2025-2026",
  "identifier": "S 1006",
  "title": "Capital Projects Sales Tax",
  "from_organization": "~{\"classification\": \"upper\"}",
  "classification": [
    "bill"
  ],
  "subject": [],
  "abstracts": [
    {
      "note": "description",
      "abstract": "A BILL TO AMEND THE SOUTH CAROLINA CODE OF LAWS BY AMENDING SECTION 4-10-330, RELATING TO THE CAPITAL PROJECTS SALES TAX, SO AS TO DESIGNATE GREENSPACE AND GREENBELT PROGRAMS AS A QUALIFYING PROJECT."
    }
  ],
  "other_titles": [],
  "other_identifiers": [
    {
      "identifier": "ocd-bill-sc-2025_2026-s1006"
    }
  ],
  "actions": [
    {
      "description": "Introduced and read first time",
      "date": "2026-03-11",
      "organization_id": "~{\"classification\": \"upper\"}",
      "classification": [
        "introduction",
        "reading-1"
      ],
      "related_entities": [],
      "_processing": {
        "log_file_created": "2026-07-14T13:54:36Z"
      }
    },
    {
      "description": "Referred to Committee on Finance",
      "date": "2026-03-11",
      "organization_id": "~{\"classification\": \"upper\"}",
      "classification": [
        "referral-committee"
      ],
      "related_entities": [],
      "_processing": {
        "log_file_created": "2026-07-14T13:54:36Z"
      }
    }
  ],
  "sponsorships": [
    {
      "name": "Davis",
      "classification": "primary",
      "entity_type": "person",
      "primary": true,
      "person_id": "~{\"chamber\": \"upper\", \"name\": \"Davis\"}",
      "organization_id": null
    }
  ],
  "related_bills": [],
  "versions": [
    {
      "note": "03/11/2026",
      "links": [
        {
          "url": "https://www.scstatehouse.gov/sess126_2025-2026/prever/1006_20260311.htm",
          "media_type": "text/html"
        }
      ],
      "date": "",
      "classification": ""
    },
    {
      "note": "Filed",
      "links": [
        {
          "url": "https://www.scstatehouse.gov/sess126_2025-2026/bills/1006.htm",
          "media_type": "text/html"
        },
        {
          "url": "https://www.scstatehouse.gov/sess126_2025-2026/bills/1006.docx",
          "media_type": "application/vnd.openxmlformats-officedocument.wordprocessingml.document"
        }
      ],
      "date": "",
      "classification": ""
    }
  ],
  "documents": [],
  "citations": [],
  "sources": [
    {
      "url": "https://www.scstatehouse.gov/billsearch.php?billnumbers=1006&session=126&summary=B",
      "note": ""
    }
  ],
  "extras": {},
  "jurisdiction": {
    "id": "ocd-jurisdiction/country:us/state:sc/government",
    "name": "South Carolina",
    "classification": "state",
    "division_id": "ocd-division/country:us/state:sc"
  },
  "_processing": {
    "logs_latest_update": "2026-07-14T13:54:36Z"
  }
}