{
  "legislative_session": "2025-2026",
  "identifier": "H 4622",
  "title": "Equal Parenting Act",
  "from_organization": "~{\"classification\": \"lower\"}",
  "classification": [
    "bill"
  ],
  "subject": [],
  "abstracts": [
    {
      "note": "description",
      "abstract": "A BILL TO AMEND THE SOUTH CAROLINA CODE OF LAWS BY ENACTING THE \"EQUAL PARENTING ACT\"; BY AMENDING SECTIONS 63-3-810, 63-3-820, 63-3-830, 63-3-850, AND 63-3-870, ALL RELATING TO GUARDIANS AD LITEM APPOINTED IN PRIVATE FAMILY COURT ACTIONS, SO AS TO PROVIDE CERTAIN PROTECTIONS AGAINST GUARDIAN AD LITEM BIAS OR OTHER MISCONDUCT, TO CLARIFY THAT EQUAL PARENTING TIME FOR BOTH PARENTS IS PRESUMED TO BE IN A CHILD'S BEST INTEREST, AND TO ADDRESS THE APPORTIONMENT OF FEES AND COSTS; BY AMENDING SECTIONS 63-15-210, 63-15-220, 63-15-230, AND 63-15-240, ALL RELATING TO CHILD CUSTODY HEARINGS, SO AS TO PROVIDE THAT EQUAL PARENTING TIME IS PRESUMED TO BE IN A CHILD'S BEST INTEREST IN CHILD CUSTODY ACTIONS, THAT PARENTAL INTERFERENCE WITH THE PARENTING TIME OF THE OTHER PARENT IS GROUNDS FOR MODIFICATION OF A CHILD CUSTODY ORDER; AND FOR OTHER PURPOSES."
    }
  ],
  "other_titles": [],
  "other_identifiers": [
    {
      "identifier": "ocd-bill-sc-2025_2026-h4622"
    }
  ],
  "actions": [
    {
      "description": "Prefiled",
      "date": "2025-12-16",
      "organization_id": "~{\"classification\": \"lower\"}",
      "classification": [
        "filing"
      ],
      "related_entities": [],
      "_processing": {
        "log_file_created": "2026-07-14T13:54:35Z"
      }
    },
    {
      "description": "Referred to Committee on Judiciary",
      "date": "2025-12-16",
      "organization_id": "~{\"classification\": \"lower\"}",
      "classification": [
        "referral-committee"
      ],
      "related_entities": [],
      "_processing": {
        "log_file_created": "2026-07-14T13:54:35Z"
      }
    },
    {
      "description": "Introduced and read first time",
      "date": "2026-01-13",
      "organization_id": "~{\"classification\": \"lower\"}",
      "classification": [
        "introduction",
        "reading-1"
      ],
      "related_entities": [],
      "_processing": {
        "log_file_created": "2026-07-14T13:54:35Z"
      }
    },
    {
      "description": "Referred to Committee on Judiciary",
      "date": "2026-01-13",
      "organization_id": "~{\"classification\": \"lower\"}",
      "classification": [
        "referral-committee"
      ],
      "related_entities": [],
      "_processing": {
        "log_file_created": "2026-07-14T13:54:35Z"
      }
    },
    {
      "description": "Member(s) request name added as sponsor: Caskey",
      "date": "2026-01-14",
      "organization_id": "~{\"classification\": \"lower\"}",
      "classification": [],
      "related_entities": [],
      "_processing": {
        "log_file_created": "2026-07-14T13:54:35Z"
      }
    },
    {
      "description": "Member(s) request name added as sponsor: Landing",
      "date": "2026-01-15",
      "organization_id": "~{\"classification\": \"lower\"}",
      "classification": [],
      "related_entities": [],
      "_processing": {
        "log_file_created": "2026-07-14T13:54:35Z"
      }
    },
    {
      "description": "Member(s) request name added as sponsor: Ford",
      "date": "2026-01-22",
      "organization_id": "~{\"classification\": \"lower\"}",
      "classification": [],
      "related_entities": [],
      "_processing": {
        "log_file_created": "2026-07-14T13:54:35Z"
      }
    },
    {
      "description": "Member(s) request name added as sponsor: Willis, Erickson, Bradley",
      "date": "2026-01-28",
      "organization_id": "~{\"classification\": \"lower\"}",
      "classification": [],
      "related_entities": [],
      "_processing": {
        "log_file_created": "2026-07-14T13:54:35Z"
      }
    },
    {
      "description": "Member(s) request name added as sponsor: Bowers, Vaughan",
      "date": "2026-02-03",
      "organization_id": "~{\"classification\": \"lower\"}",
      "classification": [],
      "related_entities": [],
      "_processing": {
        "log_file_created": "2026-07-14T13:54:35Z"
      }
    },
    {
      "description": "Member(s) request name added as sponsor: J.L.Johnson",
      "date": "2026-02-05",
      "organization_id": "~{\"classification\": \"lower\"}",
      "classification": [],
      "related_entities": [],
      "_processing": {
        "log_file_created": "2026-07-14T13:54:35Z"
      }
    },
    {
      "description": "Member(s) request name added as sponsor: Lastinger",
      "date": "2026-02-24",
      "organization_id": "~{\"classification\": \"lower\"}",
      "classification": [],
      "related_entities": [],
      "_processing": {
        "log_file_created": "2026-07-14T13:54:35Z"
      }
    },
    {
      "description": "Member(s) request name added as sponsor: Burns",
      "date": "2026-03-31",
      "organization_id": "~{\"classification\": \"lower\"}",
      "classification": [],
      "related_entities": [],
      "_processing": {
        "log_file_created": "2026-07-14T13:54:35Z"
      }
    },
    {
      "description": "Member(s) request name added as sponsor: Alexander",
      "date": "2026-04-29",
      "organization_id": "~{\"classification\": \"lower\"}",
      "classification": [],
      "related_entities": [],
      "_processing": {
        "log_file_created": "2026-07-14T13:54:35Z"
      }
    }
  ],
  "sponsorships": [
    {
      "name": "Gatch",
      "classification": "primary",
      "entity_type": "person",
      "primary": true,
      "person_id": "~{\"chamber\": \"lower\", \"name\": \"Gatch\"}",
      "organization_id": null
    },
    {
      "name": "Brewer",
      "classification": "primary",
      "entity_type": "person",
      "primary": true,
      "person_id": "~{\"chamber\": \"lower\", \"name\": \"Brewer\"}",
      "organization_id": null
    },
    {
      "name": "Edgerton",
      "classification": "primary",
      "entity_type": "person",
      "primary": true,
      "person_id": "~{\"chamber\": \"lower\", \"name\": \"Edgerton\"}",
      "organization_id": null
    },
    {
      "name": "Gagnon",
      "classification": "primary",
      "entity_type": "person",
      "primary": true,
      "person_id": "~{\"chamber\": \"lower\", \"name\": \"Gagnon\"}",
      "organization_id": null
    },
    {
      "name": "Guffey",
      "classification": "primary",
      "entity_type": "person",
      "primary": true,
      "person_id": "~{\"chamber\": \"lower\", \"name\": \"Guffey\"}",
      "organization_id": null
    },
    {
      "name": "Martin",
      "classification": "primary",
      "entity_type": "person",
      "primary": true,
      "person_id": "~{\"chamber\": \"lower\", \"name\": \"Martin\"}",
      "organization_id": null
    },
    {
      "name": "Long",
      "classification": "primary",
      "entity_type": "person",
      "primary": true,
      "person_id": "~{\"chamber\": \"lower\", \"name\": \"Long\"}",
      "organization_id": null
    },
    {
      "name": "Sessions",
      "classification": "primary",
      "entity_type": "person",
      "primary": true,
      "person_id": "~{\"chamber\": \"lower\", \"name\": \"Sessions\"}",
      "organization_id": null
    },
    {
      "name": "M.M. Smith",
      "classification": "primary",
      "entity_type": "person",
      "primary": true,
      "person_id": "~{\"chamber\": \"lower\", \"name\": \"M.M. Smith\"}",
      "organization_id": null
    },
    {
      "name": "Teeple",
      "classification": "primary",
      "entity_type": "person",
      "primary": true,
      "person_id": "~{\"chamber\": \"lower\", \"name\": \"Teeple\"}",
      "organization_id": null
    },
    {
      "name": "McCravy",
      "classification": "primary",
      "entity_type": "person",
      "primary": true,
      "person_id": "~{\"chamber\": \"lower\", \"name\": \"McCravy\"}",
      "organization_id": null
    },
    {
      "name": "Pope",
      "classification": "primary",
      "entity_type": "person",
      "primary": true,
      "person_id": "~{\"chamber\": \"lower\", \"name\": \"Pope\"}",
      "organization_id": null
    },
    {
      "name": "Magnuson",
      "classification": "primary",
      "entity_type": "person",
      "primary": true,
      "person_id": "~{\"chamber\": \"lower\", \"name\": \"Magnuson\"}",
      "organization_id": null
    },
    {
      "name": "Taylor",
      "classification": "primary",
      "entity_type": "person",
      "primary": true,
      "person_id": "~{\"chamber\": \"lower\", \"name\": \"Taylor\"}",
      "organization_id": null
    },
    {
      "name": "Lawson",
      "classification": "primary",
      "entity_type": "person",
      "primary": true,
      "person_id": "~{\"chamber\": \"lower\", \"name\": \"Lawson\"}",
      "organization_id": null
    },
    {
      "name": "Caskey",
      "classification": "primary",
      "entity_type": "person",
      "primary": true,
      "person_id": "~{\"chamber\": \"lower\", \"name\": \"Caskey\"}",
      "organization_id": null
    },
    {
      "name": "Landing",
      "classification": "primary",
      "entity_type": "person",
      "primary": true,
      "person_id": "~{\"chamber\": \"lower\", \"name\": \"Landing\"}",
      "organization_id": null
    },
    {
      "name": "Ford",
      "classification": "primary",
      "entity_type": "person",
      "primary": true,
      "person_id": "~{\"chamber\": \"lower\", \"name\": \"Ford\"}",
      "organization_id": null
    },
    {
      "name": "Willis",
      "classification": "primary",
      "entity_type": "person",
      "primary": true,
      "person_id": "~{\"chamber\": \"lower\", \"name\": \"Willis\"}",
      "organization_id": null
    },
    {
      "name": "Erickson",
      "classification": "primary",
      "entity_type": "person",
      "primary": true,
      "person_id": "~{\"chamber\": \"lower\", \"name\": \"Erickson\"}",
      "organization_id": null
    },
    {
      "name": "Bradley",
      "classification": "primary",
      "entity_type": "person",
      "primary": true,
      "person_id": "~{\"chamber\": \"lower\", \"name\": \"Bradley\"}",
      "organization_id": null
    },
    {
      "name": "Bowers",
      "classification": "primary",
      "entity_type": "person",
      "primary": true,
      "person_id": "~{\"chamber\": \"lower\", \"name\": \"Bowers\"}",
      "organization_id": null
    },
    {
      "name": "Vaughan",
      "classification": "primary",
      "entity_type": "person",
      "primary": true,
      "person_id": "~{\"chamber\": \"lower\", \"name\": \"Vaughan\"}",
      "organization_id": null
    },
    {
      "name": "J.L. Johnson",
      "classification": "primary",
      "entity_type": "person",
      "primary": true,
      "person_id": "~{\"chamber\": \"lower\", \"name\": \"J.L. Johnson\"}",
      "organization_id": null
    },
    {
      "name": "Lastinger",
      "classification": "primary",
      "entity_type": "person",
      "primary": true,
      "person_id": "~{\"chamber\": \"lower\", \"name\": \"Lastinger\"}",
      "organization_id": null
    },
    {
      "name": "Burns",
      "classification": "primary",
      "entity_type": "person",
      "primary": true,
      "person_id": "~{\"chamber\": \"lower\", \"name\": \"Burns\"}",
      "organization_id": null
    },
    {
      "name": "Alexander",
      "classification": "primary",
      "entity_type": "person",
      "primary": true,
      "person_id": "~{\"chamber\": \"lower\", \"name\": \"Alexander\"}",
      "organization_id": null
    }
  ],
  "related_bills": [],
  "versions": [
    {
      "note": "12/17/2025",
      "links": [
        {
          "url": "https://www.scstatehouse.gov/sess126_2025-2026/prever/4622_20251217.htm",
          "media_type": "text/html"
        }
      ],
      "date": "",
      "classification": ""
    },
    {
      "note": "12/17/2025-A",
      "links": [
        {
          "url": "https://www.scstatehouse.gov/sess126_2025-2026/prever/4622_20251217a.htm",
          "media_type": "text/html"
        }
      ],
      "date": "",
      "classification": ""
    },
    {
      "note": "Filed",
      "links": [
        {
          "url": "https://www.scstatehouse.gov/sess126_2025-2026/bills/4622.htm",
          "media_type": "text/html"
        },
        {
          "url": "https://www.scstatehouse.gov/sess126_2025-2026/bills/4622.docx",
          "media_type": "application/vnd.openxmlformats-officedocument.wordprocessingml.document"
        }
      ],
      "date": "",
      "classification": ""
    }
  ],
  "documents": [],
  "citations": [],
  "sources": [
    {
      "url": "https://www.scstatehouse.gov/billsearch.php?billnumbers=4622&session=126&summary=B",
      "note": ""
    }
  ],
  "extras": {},
  "jurisdiction": {
    "id": "ocd-jurisdiction/country:us/state:sc/government",
    "name": "South Carolina",
    "classification": "state",
    "division_id": "ocd-division/country:us/state:sc"
  },
  "_processing": {
    "logs_latest_update": "2026-07-14T13:54:37Z",
    "text_extraction_latest_update": "2026-07-14T20:24:28.741632Z"
  }
}